{
  "id": "cove.community.scrapers.yaml.tadpolexstudio",
  "name": "TadpolexStudio",
  "version": "1.0.0",
  "description": "YAML metadata scraper for TadpolexStudio.",
  "url": "https://github.com/yourcove/communityscrapers",
  "kind": "scraper-pack",
  "minCoveVersion": "0.0.28",
  "categories": [
    "scraper",
    "metadata",
    "yaml-scraper"
  ],
  "scraperFiles": [
    "scrapers/tadpolexstudio.yml"
  ],
  "permissions": {
    "network": [
      "*.tadpolexstudio.com",
      "tadpolexstudio.com"
    ]
  }
}
